{
  "id": 116766110,
  "node_id": "MDEwOlJlcG9zaXRvcnkxMTY3NjYxMTA=",
  "name": "chrome-ssh-agent",
  "full_name": "google/chrome-ssh-agent",
  "private": false,
  "owner": {
    "login": "google",
    "id": 1342004,
    "node_id": "MDEyOk9yZ2FuaXphdGlvbjEzNDIwMDQ=",
    "avatar_url": "https://avatars.githubusercontent.com/u/1342004?v=4",
    "gravatar_id": "",
    "url": "https://api.github.com/users/google",
    "html_url": "https://github.com/google",
    "followers_url": "https://api.github.com/users/google/followers",
    "following_url": "https://api.github.com/users/google/following{/other_user}",
    "gists_url": "https://api.github.com/users/google/gists{/gist_id}",
    "starred_url": "https://api.github.com/users/google/starred{/owner}{/repo}",
    "subscriptions_url": "https://api.github.com/users/google/subscriptions",
    "organizations_url": "https://api.github.com/users/google/orgs",
    "repos_url": "https://api.github.com/users/google/repos",
    "events_url": "https://api.github.com/users/google/events{/privacy}",
    "received_events_url": "https://api.github.com/users/google/received_events",
    "type": "Organization",
    "user_view_type": "public",
    "site_admin": false
  },
  "html_url": "https://github.com/google/chrome-ssh-agent",
  "description": "SSH Agent for use with Google Chrome's Secure Shell extension",
  "fork": false,
  "url": "https://api.github.com/repos/google/chrome-ssh-agent",
  "forks_url": "https://api.github.com/repos/google/chrome-ssh-agent/forks",
  "keys_url": "https://api.github.com/repos/google/chrome-ssh-agent/keys{/key_id}",
  "collaborators_url": "https://api.github.com/repos/google/chrome-ssh-agent/collaborators{/collaborator}",
  "teams_url": "https://api.github.com/repos/google/chrome-ssh-agent/teams",
  "hooks_url": "https://api.github.com/repos/google/chrome-ssh-agent/hooks",
  "issue_events_url": "https://api.github.com/repos/google/chrome-ssh-agent/issues/events{/number}",
  "events_url": "https://api.github.com/repos/google/chrome-ssh-agent/events",
  "assignees_url": "https://api.github.com/repos/google/chrome-ssh-agent/assignees{/user}",
  "branches_url": "https://api.github.com/repos/google/chrome-ssh-agent/branches{/branch}",
  "tags_url": "https://api.github.com/repos/google/chrome-ssh-agent/tags",
  "blobs_url": "https://api.github.com/repos/google/chrome-ssh-agent/git/blobs{/sha}",
  "git_tags_url": "https://api.github.com/repos/google/chrome-ssh-agent/git/tags{/sha}",
  "git_refs_url": "https://api.github.com/repos/google/chrome-ssh-agent/git/refs{/sha}",
  "trees_url": "https://api.github.com/repos/google/chrome-ssh-agent/git/trees{/sha}",
  "statuses_url": "https://api.github.com/repos/google/chrome-ssh-agent/statuses/{sha}",
  "languages_url": "https://api.github.com/repos/google/chrome-ssh-agent/languages",
  "stargazers_url": "https://api.github.com/repos/google/chrome-ssh-agent/stargazers",
  "contributors_url": "https://api.github.com/repos/google/chrome-ssh-agent/contributors",
  "subscribers_url": "https://api.github.com/repos/google/chrome-ssh-agent/subscribers",
  "subscription_url": "https://api.github.com/repos/google/chrome-ssh-agent/subscription",
  "commits_url": "https://api.github.com/repos/google/chrome-ssh-agent/commits{/sha}",
  "git_commits_url": "https://api.github.com/repos/google/chrome-ssh-agent/git/commits{/sha}",
  "comments_url": "https://api.github.com/repos/google/chrome-ssh-agent/comments{/number}",
  "issue_comment_url": "https://api.github.com/repos/google/chrome-ssh-agent/issues/comments{/number}",
  "contents_url": "https://api.github.com/repos/google/chrome-ssh-agent/contents/{+path}",
  "compare_url": "https://api.github.com/repos/google/chrome-ssh-agent/compare/{base}...{head}",
  "merges_url": "https://api.github.com/repos/google/chrome-ssh-agent/merges",
  "archive_url": "https://api.github.com/repos/google/chrome-ssh-agent/{archive_format}{/ref}",
  "downloads_url": "https://api.github.com/repos/google/chrome-ssh-agent/downloads",
  "issues_url": "https://api.github.com/repos/google/chrome-ssh-agent/issues{/number}",
  "pulls_url": "https://api.github.com/repos/google/chrome-ssh-agent/pulls{/number}",
  "milestones_url": "https://api.github.com/repos/google/chrome-ssh-agent/milestones{/number}",
  "notifications_url": "https://api.github.com/repos/google/chrome-ssh-agent/notifications{?since,all,participating}",
  "labels_url": "https://api.github.com/repos/google/chrome-ssh-agent/labels{/name}",
  "releases_url": "https://api.github.com/repos/google/chrome-ssh-agent/releases{/id}",
  "deployments_url": "https://api.github.com/repos/google/chrome-ssh-agent/deployments",
  "created_at": "2018-01-09T04:33:08Z",
  "updated_at": "2025-05-29T02:42:06Z",
  "pushed_at": "2025-05-29T02:42:02Z",
  "git_url": "git://github.com/google/chrome-ssh-agent.git",
  "ssh_url": "git@github.com:google/chrome-ssh-agent.git",
  "clone_url": "https://github.com/google/chrome-ssh-agent.git",
  "svn_url": "https://github.com/google/chrome-ssh-agent",
  "homepage": "",
  "size": 3380,
  "stargazers_count": 268,
  "watchers_count": 268,
  "language": "Go",
  "has_issues": true,
  "has_projects": false,
  "has_downloads": false,
  "has_wiki": false,
  "has_pages": false,
  "has_discussions": false,
  "forks_count": 41,
  "mirror_url": null,
  "archived": false,
  "disabled": false,
  "open_issues_count": 14,
  "license": {
    "key": "apache-2.0",
    "name": "Apache License 2.0",
    "spdx_id": "Apache-2.0",
    "url": "https://api.github.com/licenses/apache-2.0",
    "node_id": "MDc6TGljZW5zZTI="
  },
  "allow_forking": true,
  "is_template": false,
  "web_commit_signoff_required": false,
  "topics": [
    "chrome-extension",
    "ssh-agent"
  ],
  "visibility": "public",
  "forks": 41,
  "open_issues": 14,
  "watchers": 268,
  "default_branch": "master",
  "permissions": {
    "admin": false,
    "maintain": false,
    "push": false,
    "triage": false,
    "pull": true
  },
  "custom_properties": {
    "requires_action_scanning": "false",
    "requires_two_party_review": "false"
  },
  "organization": {
    "login": "google",
    "id": 1342004,
    "node_id": "MDEyOk9yZ2FuaXphdGlvbjEzNDIwMDQ=",
    "avatar_url": "https://avatars.githubusercontent.com/u/1342004?v=4",
    "gravatar_id": "",
    "url": "https://api.github.com/users/google",
    "html_url": "https://github.com/google",
    "followers_url": "https://api.github.com/users/google/followers",
    "following_url": "https://api.github.com/users/google/following{/other_user}",
    "gists_url": "https://api.github.com/users/google/gists{/gist_id}",
    "starred_url": "https://api.github.com/users/google/starred{/owner}{/repo}",
    "subscriptions_url": "https://api.github.com/users/google/subscriptions",
    "organizations_url": "https://api.github.com/users/google/orgs",
    "repos_url": "https://api.github.com/users/google/repos",
    "events_url": "https://api.github.com/users/google/events{/privacy}",
    "received_events_url": "https://api.github.com/users/google/received_events",
    "type": "Organization",
    "user_view_type": "public",
    "site_admin": false
  },
  "network_count": 41,
  "subscribers_count": 10
}