{
  "id": 724905776,
  "node_id": "R_kgDOKzUvMA",
  "name": "dotfiles",
  "full_name": "joegesualdo/dotfiles",
  "private": false,
  "owner": {
    "login": "joegesualdo",
    "id": 2592156,
    "node_id": "MDQ6VXNlcjI1OTIxNTY=",
    "avatar_url": "https://avatars.githubusercontent.com/u/2592156?v=4",
    "gravatar_id": "",
    "url": "https://api.github.com/users/joegesualdo",
    "html_url": "https://github.com/joegesualdo",
    "followers_url": "https://api.github.com/users/joegesualdo/followers",
    "following_url": "https://api.github.com/users/joegesualdo/following{/other_user}",
    "gists_url": "https://api.github.com/users/joegesualdo/gists{/gist_id}",
    "starred_url": "https://api.github.com/users/joegesualdo/starred{/owner}{/repo}",
    "subscriptions_url": "https://api.github.com/users/joegesualdo/subscriptions",
    "organizations_url": "https://api.github.com/users/joegesualdo/orgs",
    "repos_url": "https://api.github.com/users/joegesualdo/repos",
    "events_url": "https://api.github.com/users/joegesualdo/events{/privacy}",
    "received_events_url": "https://api.github.com/users/joegesualdo/received_events",
    "type": "User",
    "user_view_type": "public",
    "site_admin": false
  },
  "html_url": "https://github.com/joegesualdo/dotfiles",
  "description": "My Dotfiles",
  "fork": false,
  "url": "https://api.github.com/repos/joegesualdo/dotfiles",
  "forks_url": "https://api.github.com/repos/joegesualdo/dotfiles/forks",
  "keys_url": "https://api.github.com/repos/joegesualdo/dotfiles/keys{/key_id}",
  "collaborators_url": "https://api.github.com/repos/joegesualdo/dotfiles/collaborators{/collaborator}",
  "teams_url": "https://api.github.com/repos/joegesualdo/dotfiles/teams",
  "hooks_url": "https://api.github.com/repos/joegesualdo/dotfiles/hooks",
  "issue_events_url": "https://api.github.com/repos/joegesualdo/dotfiles/issues/events{/number}",
  "events_url": "https://api.github.com/repos/joegesualdo/dotfiles/events",
  "assignees_url": "https://api.github.com/repos/joegesualdo/dotfiles/assignees{/user}",
  "branches_url": "https://api.github.com/repos/joegesualdo/dotfiles/branches{/branch}",
  "tags_url": "https://api.github.com/repos/joegesualdo/dotfiles/tags",
  "blobs_url": "https://api.github.com/repos/joegesualdo/dotfiles/git/blobs{/sha}",
  "git_tags_url": "https://api.github.com/repos/joegesualdo/dotfiles/git/tags{/sha}",
  "git_refs_url": "https://api.github.com/repos/joegesualdo/dotfiles/git/refs{/sha}",
  "trees_url": "https://api.github.com/repos/joegesualdo/dotfiles/git/trees{/sha}",
  "statuses_url": "https://api.github.com/repos/joegesualdo/dotfiles/statuses/{sha}",
  "languages_url": "https://api.github.com/repos/joegesualdo/dotfiles/languages",
  "stargazers_url": "https://api.github.com/repos/joegesualdo/dotfiles/stargazers",
  "contributors_url": "https://api.github.com/repos/joegesualdo/dotfiles/contributors",
  "subscribers_url": "https://api.github.com/repos/joegesualdo/dotfiles/subscribers",
  "subscription_url": "https://api.github.com/repos/joegesualdo/dotfiles/subscription",
  "commits_url": "https://api.github.com/repos/joegesualdo/dotfiles/commits{/sha}",
  "git_commits_url": "https://api.github.com/repos/joegesualdo/dotfiles/git/commits{/sha}",
  "comments_url": "https://api.github.com/repos/joegesualdo/dotfiles/comments{/number}",
  "issue_comment_url": "https://api.github.com/repos/joegesualdo/dotfiles/issues/comments{/number}",
  "contents_url": "https://api.github.com/repos/joegesualdo/dotfiles/contents/{+path}",
  "compare_url": "https://api.github.com/repos/joegesualdo/dotfiles/compare/{base}...{head}",
  "merges_url": "https://api.github.com/repos/joegesualdo/dotfiles/merges",
  "archive_url": "https://api.github.com/repos/joegesualdo/dotfiles/{archive_format}{/ref}",
  "downloads_url": "https://api.github.com/repos/joegesualdo/dotfiles/downloads",
  "issues_url": "https://api.github.com/repos/joegesualdo/dotfiles/issues{/number}",
  "pulls_url": "https://api.github.com/repos/joegesualdo/dotfiles/pulls{/number}",
  "milestones_url": "https://api.github.com/repos/joegesualdo/dotfiles/milestones{/number}",
  "notifications_url": "https://api.github.com/repos/joegesualdo/dotfiles/notifications{?since,all,participating}",
  "labels_url": "https://api.github.com/repos/joegesualdo/dotfiles/labels{/name}",
  "releases_url": "https://api.github.com/repos/joegesualdo/dotfiles/releases{/id}",
  "deployments_url": "https://api.github.com/repos/joegesualdo/dotfiles/deployments",
  "created_at": "2023-11-29T02:59:34Z",
  "updated_at": "2024-12-16T04:34:59Z",
  "pushed_at": "2024-12-16T04:34:55Z",
  "git_url": "git://github.com/joegesualdo/dotfiles.git",
  "ssh_url": "git@github.com:joegesualdo/dotfiles.git",
  "clone_url": "https://github.com/joegesualdo/dotfiles.git",
  "svn_url": "https://github.com/joegesualdo/dotfiles",
  "homepage": null,
  "size": 46,
  "stargazers_count": 0,
  "watchers_count": 0,
  "language": "Lua",
  "has_issues": true,
  "has_projects": true,
  "has_downloads": true,
  "has_wiki": true,
  "has_pages": false,
  "has_discussions": false,
  "forks_count": 0,
  "mirror_url": null,
  "archived": false,
  "disabled": false,
  "open_issues_count": 0,
  "license": null,
  "allow_forking": true,
  "is_template": false,
  "web_commit_signoff_required": false,
  "topics": [],
  "visibility": "public",
  "forks": 0,
  "open_issues": 0,
  "watchers": 0,
  "default_branch": "main",
  "permissions": {
    "admin": false,
    "maintain": false,
    "push": false,
    "triage": false,
    "pull": true
  },
  "network_count": 0,
  "subscribers_count": 1
}