{
  "id": 66886901,
  "node_id": "MDEwOlJlcG9zaXRvcnk2Njg4NjkwMQ==",
  "name": "harbor",
  "full_name": "reasonerjt/harbor",
  "private": false,
  "owner": {
    "login": "reasonerjt",
    "id": 2390463,
    "node_id": "MDQ6VXNlcjIzOTA0NjM=",
    "avatar_url": "https://avatars.githubusercontent.com/u/2390463?v=4",
    "gravatar_id": "",
    "url": "https://api.github.com/users/reasonerjt",
    "html_url": "https://github.com/reasonerjt",
    "followers_url": "https://api.github.com/users/reasonerjt/followers",
    "following_url": "https://api.github.com/users/reasonerjt/following{/other_user}",
    "gists_url": "https://api.github.com/users/reasonerjt/gists{/gist_id}",
    "starred_url": "https://api.github.com/users/reasonerjt/starred{/owner}{/repo}",
    "subscriptions_url": "https://api.github.com/users/reasonerjt/subscriptions",
    "organizations_url": "https://api.github.com/users/reasonerjt/orgs",
    "repos_url": "https://api.github.com/users/reasonerjt/repos",
    "events_url": "https://api.github.com/users/reasonerjt/events{/privacy}",
    "received_events_url": "https://api.github.com/users/reasonerjt/received_events",
    "type": "User",
    "user_view_type": "public",
    "site_admin": false
  },
  "html_url": "https://github.com/reasonerjt/harbor",
  "description": "An enterprise-class container registry server based on Docker Distribution",
  "fork": true,
  "url": "https://api.github.com/repos/reasonerjt/harbor",
  "forks_url": "https://api.github.com/repos/reasonerjt/harbor/forks",
  "keys_url": "https://api.github.com/repos/reasonerjt/harbor/keys{/key_id}",
  "collaborators_url": "https://api.github.com/repos/reasonerjt/harbor/collaborators{/collaborator}",
  "teams_url": "https://api.github.com/repos/reasonerjt/harbor/teams",
  "hooks_url": "https://api.github.com/repos/reasonerjt/harbor/hooks",
  "issue_events_url": "https://api.github.com/repos/reasonerjt/harbor/issues/events{/number}",
  "events_url": "https://api.github.com/repos/reasonerjt/harbor/events",
  "assignees_url": "https://api.github.com/repos/reasonerjt/harbor/assignees{/user}",
  "branches_url": "https://api.github.com/repos/reasonerjt/harbor/branches{/branch}",
  "tags_url": "https://api.github.com/repos/reasonerjt/harbor/tags",
  "blobs_url": "https://api.github.com/repos/reasonerjt/harbor/git/blobs{/sha}",
  "git_tags_url": "https://api.github.com/repos/reasonerjt/harbor/git/tags{/sha}",
  "git_refs_url": "https://api.github.com/repos/reasonerjt/harbor/git/refs{/sha}",
  "trees_url": "https://api.github.com/repos/reasonerjt/harbor/git/trees{/sha}",
  "statuses_url": "https://api.github.com/repos/reasonerjt/harbor/statuses/{sha}",
  "languages_url": "https://api.github.com/repos/reasonerjt/harbor/languages",
  "stargazers_url": "https://api.github.com/repos/reasonerjt/harbor/stargazers",
  "contributors_url": "https://api.github.com/repos/reasonerjt/harbor/contributors",
  "subscribers_url": "https://api.github.com/repos/reasonerjt/harbor/subscribers",
  "subscription_url": "https://api.github.com/repos/reasonerjt/harbor/subscription",
  "commits_url": "https://api.github.com/repos/reasonerjt/harbor/commits{/sha}",
  "git_commits_url": "https://api.github.com/repos/reasonerjt/harbor/git/commits{/sha}",
  "comments_url": "https://api.github.com/repos/reasonerjt/harbor/comments{/number}",
  "issue_comment_url": "https://api.github.com/repos/reasonerjt/harbor/issues/comments{/number}",
  "contents_url": "https://api.github.com/repos/reasonerjt/harbor/contents/{+path}",
  "compare_url": "https://api.github.com/repos/reasonerjt/harbor/compare/{base}...{head}",
  "merges_url": "https://api.github.com/repos/reasonerjt/harbor/merges",
  "archive_url": "https://api.github.com/repos/reasonerjt/harbor/{archive_format}{/ref}",
  "downloads_url": "https://api.github.com/repos/reasonerjt/harbor/downloads",
  "issues_url": "https://api.github.com/repos/reasonerjt/harbor/issues{/number}",
  "pulls_url": "https://api.github.com/repos/reasonerjt/harbor/pulls{/number}",
  "milestones_url": "https://api.github.com/repos/reasonerjt/harbor/milestones{/number}",
  "notifications_url": "https://api.github.com/repos/reasonerjt/harbor/notifications{?since,all,participating}",
  "labels_url": "https://api.github.com/repos/reasonerjt/harbor/labels{/name}",
  "releases_url": "https://api.github.com/repos/reasonerjt/harbor/releases{/id}",
  "deployments_url": "https://api.github.com/repos/reasonerjt/harbor/deployments",
  "created_at": "2016-08-29T22:59:08Z",
  "updated_at": "2021-09-24T10:25:57Z",
  "pushed_at": "2025-05-15T06:02:39Z",
  "git_url": "git://github.com/reasonerjt/harbor.git",
  "ssh_url": "git@github.com:reasonerjt/harbor.git",
  "clone_url": "https://github.com/reasonerjt/harbor.git",
  "svn_url": "https://github.com/reasonerjt/harbor",
  "homepage": "http://vmware.github.io/harbor/",
  "size": 209273,
  "stargazers_count": 0,
  "watchers_count": 0,
  "language": "Go",
  "has_issues": false,
  "has_projects": true,
  "has_downloads": true,
  "has_wiki": true,
  "has_pages": false,
  "has_discussions": false,
  "forks_count": 1,
  "mirror_url": null,
  "archived": false,
  "disabled": false,
  "open_issues_count": 0,
  "license": {
    "key": "apache-2.0",
    "name": "Apache License 2.0",
    "spdx_id": "Apache-2.0",
    "url": "https://api.github.com/licenses/apache-2.0",
    "node_id": "MDc6TGljZW5zZTI="
  },
  "allow_forking": true,
  "is_template": false,
  "web_commit_signoff_required": false,
  "topics": [],
  "visibility": "public",
  "forks": 1,
  "open_issues": 0,
  "watchers": 0,
  "default_branch": "master",
  "permissions": {
    "admin": false,
    "maintain": false,
    "push": false,
    "triage": false,
    "pull": true
  },
  "parent": {
    "id": 50613991,
    "node_id": "MDEwOlJlcG9zaXRvcnk1MDYxMzk5MQ==",
    "name": "harbor",
    "full_name": "goharbor/harbor",
    "private": false,
    "owner": {
      "login": "goharbor",
      "id": 40275816,
      "node_id": "MDEyOk9yZ2FuaXphdGlvbjQwMjc1ODE2",
      "avatar_url": "https://avatars.githubusercontent.com/u/40275816?v=4",
      "gravatar_id": "",
      "url": "https://api.github.com/users/goharbor",
      "html_url": "https://github.com/goharbor",
      "followers_url": "https://api.github.com/users/goharbor/followers",
      "following_url": "https://api.github.com/users/goharbor/following{/other_user}",
      "gists_url": "https://api.github.com/users/goharbor/gists{/gist_id}",
      "starred_url": "https://api.github.com/users/goharbor/starred{/owner}{/repo}",
      "subscriptions_url": "https://api.github.com/users/goharbor/subscriptions",
      "organizations_url": "https://api.github.com/users/goharbor/orgs",
      "repos_url": "https://api.github.com/users/goharbor/repos",
      "events_url": "https://api.github.com/users/goharbor/events{/privacy}",
      "received_events_url": "https://api.github.com/users/goharbor/received_events",
      "type": "Organization",
      "user_view_type": "public",
      "site_admin": false
    },
    "html_url": "https://github.com/goharbor/harbor",
    "description": "An open source trusted cloud native registry project that stores, signs, and scans content.",
    "fork": false,
    "url": "https://api.github.com/repos/goharbor/harbor",
    "forks_url": "https://api.github.com/repos/goharbor/harbor/forks",
    "keys_url": "https://api.github.com/repos/goharbor/harbor/keys{/key_id}",
    "collaborators_url": "https://api.github.com/repos/goharbor/harbor/collaborators{/collaborator}",
    "teams_url": "https://api.github.com/repos/goharbor/harbor/teams",
    "hooks_url": "https://api.github.com/repos/goharbor/harbor/hooks",
    "issue_events_url": "https://api.github.com/repos/goharbor/harbor/issues/events{/number}",
    "events_url": "https://api.github.com/repos/goharbor/harbor/events",
    "assignees_url": "https://api.github.com/repos/goharbor/harbor/assignees{/user}",
    "branches_url": "https://api.github.com/repos/goharbor/harbor/branches{/branch}",
    "tags_url": "https://api.github.com/repos/goharbor/harbor/tags",
    "blobs_url": "https://api.github.com/repos/goharbor/harbor/git/blobs{/sha}",
    "git_tags_url": "https://api.github.com/repos/goharbor/harbor/git/tags{/sha}",
    "git_refs_url": "https://api.github.com/repos/goharbor/harbor/git/refs{/sha}",
    "trees_url": "https://api.github.com/repos/goharbor/harbor/git/trees{/sha}",
    "statuses_url": "https://api.github.com/repos/goharbor/harbor/statuses/{sha}",
    "languages_url": "https://api.github.com/repos/goharbor/harbor/languages",
    "stargazers_url": "https://api.github.com/repos/goharbor/harbor/stargazers",
    "contributors_url": "https://api.github.com/repos/goharbor/harbor/contributors",
    "subscribers_url": "https://api.github.com/repos/goharbor/harbor/subscribers",
    "subscription_url": "https://api.github.com/repos/goharbor/harbor/subscription",
    "commits_url": "https://api.github.com/repos/goharbor/harbor/commits{/sha}",
    "git_commits_url": "https://api.github.com/repos/goharbor/harbor/git/commits{/sha}",
    "comments_url": "https://api.github.com/repos/goharbor/harbor/comments{/number}",
    "issue_comment_url": "https://api.github.com/repos/goharbor/harbor/issues/comments{/number}",
    "contents_url": "https://api.github.com/repos/goharbor/harbor/contents/{+path}",
    "compare_url": "https://api.github.com/repos/goharbor/harbor/compare/{base}...{head}",
    "merges_url": "https://api.github.com/repos/goharbor/harbor/merges",
    "archive_url": "https://api.github.com/repos/goharbor/harbor/{archive_format}{/ref}",
    "downloads_url": "https://api.github.com/repos/goharbor/harbor/downloads",
    "issues_url": "https://api.github.com/repos/goharbor/harbor/issues{/number}",
    "pulls_url": "https://api.github.com/repos/goharbor/harbor/pulls{/number}",
    "milestones_url": "https://api.github.com/repos/goharbor/harbor/milestones{/number}",
    "notifications_url": "https://api.github.com/repos/goharbor/harbor/notifications{?since,all,participating}",
    "labels_url": "https://api.github.com/repos/goharbor/harbor/labels{/name}",
    "releases_url": "https://api.github.com/repos/goharbor/harbor/releases{/id}",
    "deployments_url": "https://api.github.com/repos/goharbor/harbor/deployments",
    "created_at": "2016-01-28T21:10:28Z",
    "updated_at": "2025-07-04T16:04:29Z",
    "pushed_at": "2025-07-03T10:23:18Z",
    "git_url": "git://github.com/goharbor/harbor.git",
    "ssh_url": "git@github.com:goharbor/harbor.git",
    "clone_url": "https://github.com/goharbor/harbor.git",
    "svn_url": "https://github.com/goharbor/harbor",
    "homepage": "https://goharbor.io",
    "size": 238655,
    "stargazers_count": 25878,
    "watchers_count": 25878,
    "language": "Go",
    "has_issues": true,
    "has_projects": true,
    "has_downloads": true,
    "has_wiki": true,
    "has_pages": false,
    "has_discussions": true,
    "forks_count": 4903,
    "mirror_url": null,
    "archived": false,
    "disabled": false,
    "open_issues_count": 718,
    "license": {
      "key": "apache-2.0",
      "name": "Apache License 2.0",
      "spdx_id": "Apache-2.0",
      "url": "https://api.github.com/licenses/apache-2.0",
      "node_id": "MDc6TGljZW5zZTI="
    },
    "allow_forking": true,
    "is_template": false,
    "web_commit_signoff_required": true,
    "topics": [
      "cloud-native",
      "cncf",
      "cncf-project",
      "container",
      "container-management",
      "container-registry",
      "containers",
      "docker",
      "hacktoberfest",
      "helm",
      "kubernetes",
      "registry"
    ],
    "visibility": "public",
    "forks": 4903,
    "open_issues": 718,
    "watchers": 25878,
    "default_branch": "main"
  },
  "source": {
    "id": 50613991,
    "node_id": "MDEwOlJlcG9zaXRvcnk1MDYxMzk5MQ==",
    "name": "harbor",
    "full_name": "goharbor/harbor",
    "private": false,
    "owner": {
      "login": "goharbor",
      "id": 40275816,
      "node_id": "MDEyOk9yZ2FuaXphdGlvbjQwMjc1ODE2",
      "avatar_url": "https://avatars.githubusercontent.com/u/40275816?v=4",
      "gravatar_id": "",
      "url": "https://api.github.com/users/goharbor",
      "html_url": "https://github.com/goharbor",
      "followers_url": "https://api.github.com/users/goharbor/followers",
      "following_url": "https://api.github.com/users/goharbor/following{/other_user}",
      "gists_url": "https://api.github.com/users/goharbor/gists{/gist_id}",
      "starred_url": "https://api.github.com/users/goharbor/starred{/owner}{/repo}",
      "subscriptions_url": "https://api.github.com/users/goharbor/subscriptions",
      "organizations_url": "https://api.github.com/users/goharbor/orgs",
      "repos_url": "https://api.github.com/users/goharbor/repos",
      "events_url": "https://api.github.com/users/goharbor/events{/privacy}",
      "received_events_url": "https://api.github.com/users/goharbor/received_events",
      "type": "Organization",
      "user_view_type": "public",
      "site_admin": false
    },
    "html_url": "https://github.com/goharbor/harbor",
    "description": "An open source trusted cloud native registry project that stores, signs, and scans content.",
    "fork": false,
    "url": "https://api.github.com/repos/goharbor/harbor",
    "forks_url": "https://api.github.com/repos/goharbor/harbor/forks",
    "keys_url": "https://api.github.com/repos/goharbor/harbor/keys{/key_id}",
    "collaborators_url": "https://api.github.com/repos/goharbor/harbor/collaborators{/collaborator}",
    "teams_url": "https://api.github.com/repos/goharbor/harbor/teams",
    "hooks_url": "https://api.github.com/repos/goharbor/harbor/hooks",
    "issue_events_url": "https://api.github.com/repos/goharbor/harbor/issues/events{/number}",
    "events_url": "https://api.github.com/repos/goharbor/harbor/events",
    "assignees_url": "https://api.github.com/repos/goharbor/harbor/assignees{/user}",
    "branches_url": "https://api.github.com/repos/goharbor/harbor/branches{/branch}",
    "tags_url": "https://api.github.com/repos/goharbor/harbor/tags",
    "blobs_url": "https://api.github.com/repos/goharbor/harbor/git/blobs{/sha}",
    "git_tags_url": "https://api.github.com/repos/goharbor/harbor/git/tags{/sha}",
    "git_refs_url": "https://api.github.com/repos/goharbor/harbor/git/refs{/sha}",
    "trees_url": "https://api.github.com/repos/goharbor/harbor/git/trees{/sha}",
    "statuses_url": "https://api.github.com/repos/goharbor/harbor/statuses/{sha}",
    "languages_url": "https://api.github.com/repos/goharbor/harbor/languages",
    "stargazers_url": "https://api.github.com/repos/goharbor/harbor/stargazers",
    "contributors_url": "https://api.github.com/repos/goharbor/harbor/contributors",
    "subscribers_url": "https://api.github.com/repos/goharbor/harbor/subscribers",
    "subscription_url": "https://api.github.com/repos/goharbor/harbor/subscription",
    "commits_url": "https://api.github.com/repos/goharbor/harbor/commits{/sha}",
    "git_commits_url": "https://api.github.com/repos/goharbor/harbor/git/commits{/sha}",
    "comments_url": "https://api.github.com/repos/goharbor/harbor/comments{/number}",
    "issue_comment_url": "https://api.github.com/repos/goharbor/harbor/issues/comments{/number}",
    "contents_url": "https://api.github.com/repos/goharbor/harbor/contents/{+path}",
    "compare_url": "https://api.github.com/repos/goharbor/harbor/compare/{base}...{head}",
    "merges_url": "https://api.github.com/repos/goharbor/harbor/merges",
    "archive_url": "https://api.github.com/repos/goharbor/harbor/{archive_format}{/ref}",
    "downloads_url": "https://api.github.com/repos/goharbor/harbor/downloads",
    "issues_url": "https://api.github.com/repos/goharbor/harbor/issues{/number}",
    "pulls_url": "https://api.github.com/repos/goharbor/harbor/pulls{/number}",
    "milestones_url": "https://api.github.com/repos/goharbor/harbor/milestones{/number}",
    "notifications_url": "https://api.github.com/repos/goharbor/harbor/notifications{?since,all,participating}",
    "labels_url": "https://api.github.com/repos/goharbor/harbor/labels{/name}",
    "releases_url": "https://api.github.com/repos/goharbor/harbor/releases{/id}",
    "deployments_url": "https://api.github.com/repos/goharbor/harbor/deployments",
    "created_at": "2016-01-28T21:10:28Z",
    "updated_at": "2025-07-04T16:04:29Z",
    "pushed_at": "2025-07-03T10:23:18Z",
    "git_url": "git://github.com/goharbor/harbor.git",
    "ssh_url": "git@github.com:goharbor/harbor.git",
    "clone_url": "https://github.com/goharbor/harbor.git",
    "svn_url": "https://github.com/goharbor/harbor",
    "homepage": "https://goharbor.io",
    "size": 238655,
    "stargazers_count": 25878,
    "watchers_count": 25878,
    "language": "Go",
    "has_issues": true,
    "has_projects": true,
    "has_downloads": true,
    "has_wiki": true,
    "has_pages": false,
    "has_discussions": true,
    "forks_count": 4903,
    "mirror_url": null,
    "archived": false,
    "disabled": false,
    "open_issues_count": 718,
    "license": {
      "key": "apache-2.0",
      "name": "Apache License 2.0",
      "spdx_id": "Apache-2.0",
      "url": "https://api.github.com/licenses/apache-2.0",
      "node_id": "MDc6TGljZW5zZTI="
    },
    "allow_forking": true,
    "is_template": false,
    "web_commit_signoff_required": true,
    "topics": [
      "cloud-native",
      "cncf",
      "cncf-project",
      "container",
      "container-management",
      "container-registry",
      "containers",
      "docker",
      "hacktoberfest",
      "helm",
      "kubernetes",
      "registry"
    ],
    "visibility": "public",
    "forks": 4903,
    "open_issues": 718,
    "watchers": 25878,
    "default_branch": "main"
  },
  "network_count": 4903,
  "subscribers_count": 2
}